my_calc/calculator.py
calculator_test_oss-0.0.1.dist-info/METADATA
calculator_test_oss-0.0.1.dist-info/WHEEL
calculator_test_oss-0.0.1.dist-info/top_level.txt
calculator_test_oss-0.0.1.dist-info/RECORD
